plainml/__init__.py
plainml-0.1.dist-info/LICENSE
plainml-0.1.dist-info/METADATA
plainml-0.1.dist-info/WHEEL
plainml-0.1.dist-info/top_level.txt
plainml-0.1.dist-info/RECORD
