Metadata-Version: 2.1
Name: plainml
Version: 0.1
Summary: UNKNOWN
Home-page: https://github.com/bistcuite/plainml
License: UNKNOWN
Platform: UNKNOWN
License-File: LICENSE
Requires-Dist: scikit-learn
Requires-Dist: numpy
Requires-Dist: pandas
Requires-Dist: joblib
Requires-Dist: matplotlib
